aliyunsdkecs_workbench/__init__.py
aliyunsdkecs_workbench/request/__init__.py
aliyunsdkecs_workbench/request/v20220220/GetInstanceRecordConfigRequest.py
aliyunsdkecs_workbench/request/v20220220/ListInstanceRecordsRequest.py
aliyunsdkecs_workbench/request/v20220220/ListTerminalCommandsRequest.py
aliyunsdkecs_workbench/request/v20220220/LoginInstanceRequest.py
aliyunsdkecs_workbench/request/v20220220/SetInstanceRecordConfigRequest.py
aliyunsdkecs_workbench/request/v20220220/ViewInstanceRecordsRequest.py
aliyunsdkecs_workbench/request/v20220220/__init__.py
aliyun_python_sdk_ecs_workbench-1.0.4.dist-info/LICENSE
aliyun_python_sdk_ecs_workbench-1.0.4.dist-info/METADATA
aliyun_python_sdk_ecs_workbench-1.0.4.dist-info/WHEEL
aliyun_python_sdk_ecs_workbench-1.0.4.dist-info/top_level.txt
aliyun_python_sdk_ecs_workbench-1.0.4.dist-info/RECORD
